prog_algs/__init__.py
prog_algs/metrics/__init__.py
prog_algs/metrics/samples.py
prog_algs/metrics/toe_metrics.py
prog_algs/metrics/toe_profile_metrics.py
prog_algs/metrics/uncertain_data_metrics.py
prog_algs/predictors/__init__.py
prog_algs/predictors/monte_carlo.py
prog_algs/predictors/prediction.py
prog_algs/predictors/predictor.py
prog_algs/predictors/toe_prediction_profile.py
prog_algs/predictors/unscented_transform.py
prog_algs/state_estimators/__init__.py
prog_algs/state_estimators/kalman_filter.py
prog_algs/state_estimators/particle_filter.py
prog_algs/state_estimators/state_estimator.py
prog_algs/state_estimators/unscented_kalman_filter.py
prog_algs/uncertain_data/__init__.py
prog_algs/uncertain_data/multivariate_normal_dist.py
prog_algs/uncertain_data/scalar_data.py
prog_algs/uncertain_data/uncertain_data.py
prog_algs/uncertain_data/unweighted_samples.py
prog_algs/utils/__init__.py
prog_algs/utils/table.py
prog_algs/visualize/__init__.py
prog_algs/visualize/plot_hist.py
prog_algs/visualize/plot_scatter.py
prog_algs-1.5.1.dist-info/METADATA
prog_algs-1.5.1.dist-info/WHEEL
prog_algs-1.5.1.dist-info/top_level.txt
prog_algs-1.5.1.dist-info/RECORD
