Metadata-Version: 2.1
Name: prog-algs
Version: 1.5.1
Summary: The NASA Prognostics Algorithm Package is a framework for model-based prognostics (computation of remaining useful life) of engineering systems. It includes algorithms for state estimation and prediction, including uncertainty propagation. The algorithms use prognostic models (see prog_models) to perform estimation and prediction. The package enables rapid development of prognostics solutions for given models of components and systems. Algorithms can be swapped for comparative studies a
Home-page: https://nasa.github.io/progpy/prog_algs_guide.html
Author: Christopher Teubert
Author-email: christopher.a.teubert@nasa.gov
License: NOSA
Project-URL: Bug Reports, https://github.com/nasa/prog_algs/issues
Project-URL: Docs, https://nasa.github.io/progpy/prog_algs_guide.html
Project-URL: Organization, https://www.nasa.gov/content/diagnostics-prognostics
Project-URL: Source, https://github.com/nasa/prog_algs
Keywords: prognostics,diagnostics,fault detection,fdir,prognostics and health management,PHM,health management,ivhm
Classifier: Development Status :: 5 - Production/Stable
Classifier: Intended Audience :: Science/Research
Classifier: Intended Audience :: Developers
Classifier: Intended Audience :: Manufacturing
Classifier: Topic :: Scientific/Engineering
Classifier: Topic :: Scientific/Engineering :: Artificial Intelligence
Classifier: Topic :: Scientific/Engineering :: Physics
Classifier: License :: Other/Proprietary License 
Classifier: Programming Language :: Python :: 3
Classifier: Programming Language :: Python :: 3.7
Classifier: Programming Language :: Python :: 3.8
Classifier: Programming Language :: Python :: 3.9
Classifier: Programming Language :: Python :: 3.10
Classifier: Programming Language :: Python :: 3 :: Only
Requires-Python: >=3.7, <3.12
Requires-Dist: numpy
Requires-Dist: scipy
Requires-Dist: filterpy
Requires-Dist: matplotlib
Requires-Dist: prog-models >=1.5.0
